.gitignore
AUTHORS.txt
COPYING
MANIFEST.in
NEWS.txt
README.txt
TODO
setup.cfg
setup.py
yould/__init__.py
yould/config.py
yould/dl-de.py
yould/dl-fr.py
yould/dl-kjb.py
yould/dl-lang.py
yould/dom.py
yould/generate.py
yould/prob.py
yould/train.py
yould.egg-info/PKG-INFO
yould.egg-info/SOURCES.txt
yould.egg-info/dependency_links.txt
yould.egg-info/entry_points.txt
yould.egg-info/top_level.txt
yould/data/__init__.py
yould/data/trainsets/__init__.py
yould/data/trainsets/de.yould
yould/data/trainsets/en.yould
yould/data/trainsets/fi.yould
yould/data/trainsets/fr.yould
yould/data/trainsets/it.yould
yould/data/trainsets/kjb.yould
yould/data/trainsets/nl.yould
