Metadata-Version: 1.0
Name: yould
Version: 0.3.7
Summary: a word generator
Home-page: http://ygingras.net/b/tag/yould
Author: Yannick Gingras
Author-email: ygingras@ygingras.net
License: GPL v3 or later
Platform: UNKNOWN
